tests/__init__.py
tests/unit/test_gesture_file_to_audio.py
tests/unit/test_gesture_file_to_motor_file.py
tests/unit/test_get_param_info.py
tests/unit/test_synth_block.py
tests/unit/test_get_shape.py
tests/unit/test_phoneme_file_to_gesture_file.py
tests/unit/__init__.py
tests/unit/test_calculate_tongueroot_automatically.py
tests/unit/test_tract_state_to_svg.py
tests/unit/test_get_constants.py
tests/unit/test_tract_state_to_tube_state.py
tests/unit/test_motor_file_to_audio_file.py
tests/unit/test_tract_state_to_transfer_function.py
tests/unit/test_get_version.py
tests/unit/test_get_gesture_duration.py
tests/unit/resources/valid_phoneme_sequence.txt
tests/unit/resources/invalid_gestural_score.txt
tests/unit/resources/valid_motor_series.txt
tests/unit/resources/valid_gestural_score.txt
vocaltractlab_cython/__init__.py
vocaltractlab_cython/libVocalTractLabApi.dylib
vocaltractlab_cython/VocalTractLabApi.c
vocaltractlab_cython/VocalTractLabApi.cpython-310-darwin.so
vocaltractlab_cython/utils.py
vocaltractlab_cython/exceptions.py
vocaltractlab_cython/VocalTractLabApi.pyx
vocaltractlab_cython/cVocalTractLabApi.pxd
vocaltractlab_cython/VocalTractLabApi.h
vocaltractlab_cython/resources/JD3.speaker
vocaltractlab_cython-0.0.16.dist-info/RECORD
vocaltractlab_cython-0.0.16.dist-info/WHEEL
vocaltractlab_cython-0.0.16.dist-info/top_level.txt
vocaltractlab_cython-0.0.16.dist-info/METADATA
vocaltractlab_cython-0.0.16.dist-info/licenses/LICENSE
